hab/__init__.py
hab/__main__.py
hab/cache.py
hab/cli.py
hab/entry_points.py
hab/errors.py
hab/formatter.py
hab/launcher.py
hab/merge_dict.py
hab/resolver.py
hab/site.py
hab/solvers.py
hab/user_prefs.py
hab/utils.py
hab/version.py
hab/distro_finders/__init__.py
hab/distro_finders/cloud_zip.py
hab/distro_finders/df_zip.py
hab/distro_finders/distro_finder.py
hab/distro_finders/s3_zip.py
hab/distro_finders/zip_sidecar.py
hab/parsers/__init__.py
hab/parsers/config.py
hab/parsers/distro.py
hab/parsers/distro_version.py
hab/parsers/flat_config.py
hab/parsers/format_parser.py
hab/parsers/hab_base.py
hab/parsers/lazy_distro_version.py
hab/parsers/meta.py
hab/parsers/placeholder.py
hab/parsers/stub_distro_version.py
hab/parsers/unfrozen_config.py
hab/templates/alias.bat
hab/templates/config.bat
hab/templates/config.ps1
hab/templates/config.sh
hab-0.51.0.data/scripts/.hab-complete.bash
hab-0.51.0.data/scripts/hab
hab-0.51.0.data/scripts/hab.bat
hab-0.51.0.data/scripts/hab.ps1
hab-0.51.0.dist-info/licenses/LICENSE
hab-0.51.0.dist-info/METADATA
hab-0.51.0.dist-info/WHEEL
hab-0.51.0.dist-info/top_level.txt
hab-0.51.0.dist-info/RECORD
