Metadata-Version: 2.4
Name: hab
Version: 0.51.0
Summary: An environment configuration and launcher system
Author-email: Blur Studio <opensource@blur.com>
License: LGPL-3.0
Project-URL: Homepage, https://github.com/blurstudio/hab
Project-URL: Source, https://github.com/blurstudio/hab
Project-URL: Tracker, https://github.com/blurstudio/hab/issues
Platform: any
Classifier: Development Status :: 5 - Production/Stable
Classifier: Environment :: Console
Classifier: Intended Audience :: Developers
Classifier: License :: OSI Approved :: GNU Lesser General Public License v3 (LGPLv3)
Classifier: Operating System :: OS Independent
Classifier: Programming Language :: Python
Classifier: Programming Language :: Python :: 3
Classifier: Programming Language :: Python :: 3 :: Only
Classifier: Programming Language :: Python :: Implementation :: CPython
Classifier: Programming Language :: Python :: Implementation :: PyPy
Requires-Python: >=3.7
License-File: LICENSE
Requires-Dist: Jinja2>=2.10.1
Requires-Dist: MarkupSafe>=0.23
Requires-Dist: Pygments
Requires-Dist: anytree
Requires-Dist: click>=7.1.2
Requires-Dist: colorama
Requires-Dist: dep-logic; python_version >= "3.8"
Requires-Dist: future>=0.18.2
Requires-Dist: importlib-metadata
Requires-Dist: packaging>=20.0
Requires-Dist: setuptools-scm[toml]>=4
Provides-Extra: cloud
Requires-Dist: cloudpathlib; extra == "cloud"
Requires-Dist: remotezip; extra == "cloud"
Provides-Extra: dev
Requires-Dist: black==22.12.0; extra == "dev"
Requires-Dist: covdefaults; extra == "dev"
Requires-Dist: coverage; extra == "dev"
Requires-Dist: flake8==5.0.4; extra == "dev"
Requires-Dist: flake8-bugbear==22.12.6; extra == "dev"
Requires-Dist: Flake8-pyproject; extra == "dev"
Requires-Dist: isort; extra == "dev"
Requires-Dist: pep8-naming==0.13.3; extra == "dev"
Requires-Dist: pytest; extra == "dev"
Requires-Dist: tox; extra == "dev"
Requires-Dist: build; extra == "dev"
Provides-Extra: json5
Requires-Dist: pyjson5; extra == "json5"
Provides-Extra: s3
Requires-Dist: cloudpathlib[s3]; extra == "s3"
Requires-Dist: remotezip; extra == "s3"
Requires-Dist: requests-aws4auth; extra == "s3"
Dynamic: license-file
